uniquecode_nudzimisiediy/__init__.py
uniquecode_nudzimisiediy/uniquecode.py
uniquecode_nudzimisiediy-0.0.1.dist-info/METADATA
uniquecode_nudzimisiediy-0.0.1.dist-info/WHEEL
uniquecode_nudzimisiediy-0.0.1.dist-info/licenses/LICENCE
uniquecode_nudzimisiediy-0.0.1.dist-info/RECORD
