Metadata-Version: 2.1
Name: uniquecode_nudzimisiediy
Version: 0.0.1
Summary: unique codename generator
Author-email: Marcin Kallas <marcin.kallas@gmail.com>
License-File: LICENCE
Classifier: License :: OSI Approved :: MIT License
Classifier: Operating System :: OS Independent
Classifier: Programming Language :: Python :: 3
Requires-Python: >=3.7
